automateda11y/__init__.py
automateda11y/pw/__init__.py
automateda11y/pw/axerunner.py
automateda11y/pw/htmlcsrunner.py
automateda11y/pw/settings.py
automateda11y/pw/a11y/__init__.py
automateda11y/pw/a11y/engine.py
automateda11y/pw/modal/__init__.py
automateda11y/pw/modal/params.py
automateda11y/pw/modal/axe/__init__.py
automateda11y/pw/modal/axe/checks.py
automateda11y/pw/modal/axe/data.py
automateda11y/pw/modal/axe/issues.py
automateda11y/pw/modal/axe/issuetype.py
automateda11y/pw/modal/axe/node.py
automateda11y/pw/modal/axe/relatednode.py
automateda11y/pw/modal/axe/runonly.py
automateda11y/pw/modal/axe/testengine.py
automateda11y/pw/modal/axe/testenvironment.py
automateda11y/pw/modal/axe/testrunner.py
automateda11y/pw/modal/axe/tooloptions.py
automateda11y/pw/modal/htmlcs/__init__.py
automateda11y/pw/modal/htmlcs/issue.py
automateda11y/pw/modal/htmlcs/issues.py
automateda11y/pw/resources/__init__.py
automateda11y/pw/resources/js/axe.js
automateda11y/pw/resources/js/htmlcs.js
automateda11y/pw/util/__init__.py
automateda11y/pw/util/a11y.py
python_a11y_playwright-1.0.1.dist-info/LICENSE
python_a11y_playwright-1.0.1.dist-info/METADATA
python_a11y_playwright-1.0.1.dist-info/WHEEL
python_a11y_playwright-1.0.1.dist-info/top_level.txt
python_a11y_playwright-1.0.1.dist-info/RECORD
