Metadata-Version: 2.1
Name: python-a11y-playwright
Version: 1.0.1
Summary: Automate Web Accessibility Testing using AXE/HTMLCS with Playwright Python
Author-email: Sridhar Bandi <sridhar.bandi.ece@gmail.com>
License: MIT License
Project-URL: Homepage, https://github.com/automated-a11y/python-a11y-playwright
Project-URL: repository, https://github.com/automated-a11y/python-a11y-playwright.git
Keywords: axe,htmlcs,accessibility,playwright
Classifier: License :: OSI Approved :: MIT License
Classifier: Programming Language :: Python
Classifier: Programming Language :: Python :: 3
Classifier: Programming Language :: Python :: 3.6
Classifier: Programming Language :: Python :: 3.7
Classifier: Programming Language :: Python :: 3.8
Classifier: Programming Language :: Python :: 3.9
Classifier: Programming Language :: Python :: 3.10
Classifier: Programming Language :: Python :: 3.11
Requires-Python: >=3.7
License-File: LICENSE
Requires-Dist: marshmallow-dataclass
